<?xml version="1.0"?>

<!DOCTYPE suppressions PUBLIC
        "-//Puppy Crawl//DTD Suppressions 1.0//EN"
        "http://www.puppycrawl.com/dtds/suppressions_1_0.dtd">

<suppressions>
    <suppress checks="JavadocMethod"  files="[\\/]Main\.java$"/>
    <suppress checks="JavadocMethod"  files="[\\/]*Controller*\.java$"/>
    <suppress checks="JavadocMethod"  files="[\\/]*View*\.java$"/>
    <suppress checks="JavadocMethod"  files="[\\/]*Manager*\.java$"/>
    <suppress checks="JavadocType"  files="[\\/]Main\.java$"/>
    <suppress checks="JavadocType"  files="[\\/]*Controller*\.java$"/>
    <suppress checks="JavadocType"  files="[\\/]*Manager*\.java$"/>
    <suppress checks="JavadocType"  files="[\\/]*View*\.java$"/>
    <suppress checks="JavadocMethod"  files="[\\/]Matrix\.java$" lines="30-42"/>
    <suppress checks="JavadocMethod"  files="[\\/]Game\.java$" lines="27"/>
    <suppress checks="JavadocMethod"  files="[\\/]MazeProcessor\.java$" lines="24"/>
    <suppress checks="JavadocMethod"  files="[\\/]AStarPathAlgorithm\.java$" lines="23"/>
    <suppress checks="JavadocMethod"  files="[\\/]Node\.java$" lines="31"/>
    <suppress checks="JavadocMethod"  files="[\\/]BinaryHeap\.java$" lines="18"/>
    <suppress checks="JavadocMethod"  files="[\\/]NormalBall\.java$" lines="22"/>
    <suppress checks="JavadocMethod"  files="[\\/]DragonBall\.java$" lines="26"/>
    <suppress checks="JavadocMethod"  files="[\\/]Ball\.java$" lines="34"/>
    <suppress checks="JavadocMethod"  files="[\\/]Inky\.java$" lines="17"/>
</suppressions>